lango_cli_beta/__init__.py
lango_cli_beta/_sample_data/adversarial_attacks_on_llms.txt
lango_cli_beta/_sample_data/diffusion_models_for_video_generation.txt
lango_cli_beta/_sample_data/generalized_visual_language_models.txt
lango_cli_beta/_sample_data/learning_with_not_enough_data_p_1_semi_supervised_learning.txt
lango_cli_beta/_sample_data/learning_with_not_enough_data_p_2_active_earning.txt
lango_cli_beta/_sample_data/learning_with_not_enough_data_p_3_data_generation.txt
lango_cli_beta/_sample_data/llm_agents.txt
lango_cli_beta/_sample_data/prompt_eng.txt
lango_cli_beta/_sample_data/thinking_about_high_quality_human_data.txt
lango_cli_beta/cli.py
lango_cli_beta/constants.py
lango_cli_beta/namespaces/chat.py
lango_cli_beta/namespaces/config.py
lango_cli_beta/namespaces/export.py
lango_cli_beta/namespaces/ingest.py
lango_cli_beta/namespaces/init.py
lango_cli_beta/namespaces/start.py
lango_cli_beta/namespaces/utils.py
lango_cli_beta/py.typed
lango_cli_beta/rag/basic_chat.py
lango_cli_beta/rag/chat.py
lango_cli_beta/rag/ingest.py
lango_cli_beta/rag/llm_chain.py
lango_cli_beta/rag/query_construction.py
lango_cli_beta/rag/types.py
lango_cli_beta/rag/utils.py
lango_cli_beta/rag_config.py
lango_cli_beta/utils.py
lango_cli_beta-0.0.1rc2.dist-info/LICENSE
lango_cli_beta-0.0.1rc2.dist-info/METADATA
lango_cli_beta-0.0.1rc2.dist-info/WHEEL
lango_cli_beta-0.0.1rc2.dist-info/entry_points.txt
lango_cli_beta-0.0.1rc2.dist-info/RECORD
