Metadata-Version: 2.1
Name: lango-cli-beta
Version: 0.0.1rc2
Summary: 
License: MIT
Requires-Python: >=3.9.0,<3.12
Classifier: License :: OSI Approved :: MIT License
Classifier: Programming Language :: Python :: 3
Classifier: Programming Language :: Python :: 3.9
Classifier: Programming Language :: Python :: 3.10
Classifier: Programming Language :: Python :: 3.11
Requires-Dist: fastapi (>=0.110.2,<1)
Requires-Dist: langchain (>=0.1.16,<0.2.0)
Requires-Dist: langchain-anthropic (>=0.1.9,<0.2.0)
Requires-Dist: langchain-cohere (>=0.1.2,<0.2.0)
Requires-Dist: langchain-community (>=0.0.34)
Requires-Dist: langchain-core (>=0.1.43,<0.2.0)
Requires-Dist: langchain-fireworks (>=0.1.2,<0.2.0)
Requires-Dist: langchain-google-vertexai (>=1.0.1,<2.0.0)
Requires-Dist: langchain-mistralai (>=0.1.2,<0.2.0)
Requires-Dist: langchain-mongodb (>=0.1.3,<0.2.0)
Requires-Dist: langchain-openai (>=0.1.3,<0.2.0)
Requires-Dist: langchain-text-splitters (>=0.0.1,<0.0.2)
Requires-Dist: langgraph (>=0.0.38,<0.1)
Requires-Dist: langserve[all] (>=0.1.0,<0.2.0)
Requires-Dist: motor (>=3.4.0,<4.0.0)
Requires-Dist: pydantic (>=1.10.13,<2)
Requires-Dist: pymongo (>=4.6.3,<5.0.0)
Requires-Dist: python-dotenv (>=1.0.1,<2.0.0)
Requires-Dist: rich (>=13.7.1,<14.0.0)
Requires-Dist: typer (>=0.9.0,<0.10.0)
Requires-Dist: unstructured[all-docs] (>=0.13.4,<0.14.0)
Requires-Dist: uvicorn (>=0.23.2,<0.24.0)
